setup.py
proso/__init__.py
proso/geography/__init__.py
proso/geography/abtesting.py
proso/geography/analysis.py
proso/geography/decorator.py
proso/geography/difficulty.py
proso/geography/graph.py
proso/geography/overtime.py
proso/geography/session.py
proso/geography/success.py
proso/geography/textstats.py
proso/geography/user.py
proso_geography_analysis.egg-info/PKG-INFO
proso_geography_analysis.egg-info/SOURCES.txt
proso_geography_analysis.egg-info/dependency_links.txt
proso_geography_analysis.egg-info/namespace_packages.txt
proso_geography_analysis.egg-info/requires.txt
proso_geography_analysis.egg-info/top_level.txt