Metadata-Version: 1.0
Name: proso-geography-analysis
Version: 0.9.7
Summary: Libs for analysis of data from PROSO Geography project
Home-page: https://github.com/proso/geography-analysis-libs/
Author: Jan Papousek
Author-email: jan.papousek@gmail.com
License: Gnu GPL v3
Platform: UNKNOWN
